pyecs/__init__.py
pyecs/__init__.pyi
pyecs/py.typed
pyecs-0.19.dist-info/LICENSE
pyecs-0.19.dist-info/WHEEL
pyecs-0.19.dist-info/METADATA
pyecs-0.19.dist-info/RECORD
