Metadata-Version: 2.1
Name: pyecs
Version: 0.19
Summary: A simple implementation of the Entity-Component pattern.
Home-page: https://github.com/timfi/pyecs
License: MIT
Author: Tim Fischer
Author-email: me@timfi.dev
Requires-Python: >=3.8,<4.0
Classifier: Development Status :: 2 - Pre-Alpha
Classifier: Intended Audience :: Developers
Classifier: License :: OSI Approved :: MIT License
Classifier: Natural Language :: English
Classifier: Operating System :: OS Independent
Classifier: Programming Language :: Python
Classifier: Programming Language :: Python :: 3
Classifier: Programming Language :: Python :: 3.8
Classifier: Programming Language :: Python :: 3.9
Classifier: Programming Language :: Python :: Implementation :: CPython
Classifier: Topic :: Games/Entertainment
Classifier: Typing :: Typed
Provides-Extra: yaml
Requires-Dist: pyyaml (>=5.4.1,<6.0.0); extra == "yaml"
Project-URL: Repository, https://github.com/timfi/pyecs
